ecoviewer/__init__.py
ecoviewer/config/__init__.py
ecoviewer/config/configutils.py
ecoviewer/constants/__init__.py
ecoviewer/constants/constants.py
ecoviewer/display/__init__.py
ecoviewer/display/displayutils.py
ecoviewer/display/graphhelper.py
ecoviewer/display/graphutils.py
ecoviewer/objects/DataManager.py
ecoviewer/objects/__init__.py
ecoviewer/objects/GraphObject/GraphObject.py
ecoviewer/objects/GraphObject/__init__.py
ecoviewer/objects/GraphObject/graphs/COPRegression.py
ecoviewer/objects/GraphObject/graphs/COPTimeseries.py
ecoviewer/objects/GraphObject/graphs/DHWBoxWhisker.py
ecoviewer/objects/GraphObject/graphs/DataStats.py
ecoviewer/objects/GraphObject/graphs/ERVPerformance.py
ecoviewer/objects/GraphObject/graphs/GPDPPHistogram.py
ecoviewer/objects/GraphObject/graphs/GPDPPTimeseries.py
ecoviewer/objects/GraphObject/graphs/HourlyShapesPlots.py
ecoviewer/objects/GraphObject/graphs/OHPPerformance.py
ecoviewer/objects/GraphObject/graphs/PeakNorm.py
ecoviewer/objects/GraphObject/graphs/PickleGraph.py
ecoviewer/objects/GraphObject/graphs/RawDataSubPlots.py
ecoviewer/objects/GraphObject/graphs/SERAMonthly.py
ecoviewer/objects/GraphObject/graphs/SERAPie.py
ecoviewer/objects/GraphObject/graphs/SummaryBarGraph.py
ecoviewer/objects/GraphObject/graphs/SummaryBarGraphLoadRatios.py
ecoviewer/objects/GraphObject/graphs/SummaryDHWTemps.py
ecoviewer/objects/GraphObject/graphs/SummaryDailyPowerByHour.py
ecoviewer/objects/GraphObject/graphs/SummaryHourlyFlow.py
ecoviewer/objects/GraphObject/graphs/SummaryPieGraph.py
ecoviewer/objects/GraphObject/graphs/__init__.py
ecoviewer-1.8.7.dist-info/licenses/LICENSE
ecoviewer-1.8.7.dist-info/METADATA
ecoviewer-1.8.7.dist-info/WHEEL
ecoviewer-1.8.7.dist-info/top_level.txt
ecoviewer-1.8.7.dist-info/RECORD
