Metadata-Version: 2.4
Name: ecoviewer
Version: 1.8.7
Summary: Contains functions for use in HVAC Dash applications
Classifier: Programming Language :: Python :: 3
Classifier: License :: OSI Approved :: GNU General Public License (GPL)
Classifier: Operating System :: OS Independent
Requires-Python: >=3.11
License-File: LICENSE
Requires-Dist: pandas>=1.5.3
Requires-Dist: plotly
Requires-Dist: dash
Requires-Dist: mysql-connector-python>=8.0.32
Requires-Dist: numpy
Dynamic: license-file
